MANIFEST.in
README.md
setup.cfg
setup.py
django_trojsten_submit.egg-info/PKG-INFO
django_trojsten_submit.egg-info/SOURCES.txt
django_trojsten_submit.egg-info/dependency_links.txt
django_trojsten_submit.egg-info/requires.txt
django_trojsten_submit.egg-info/top_level.txt
submit/__init__.py
submit/admin.py
submit/commands.py
submit/constants.py
submit/defaults.py
submit/forms.py
submit/judge_helpers.py
submit/models.py
submit/serializers.py
submit/settings.py
submit/submit_helpers.py
submit/urls.py
submit/views.py
submit/locale/sk/LC_MESSAGES/django.mo
submit/locale/sk/LC_MESSAGES/django.po
submit/migrations/0001_initial.py
submit/migrations/0002_review_filename.py
submit/migrations/0003_submitreceiver_task.py
submit/migrations/0004_auto_20170215_2007.py
submit/migrations/0005_auto_20170215_2324.py
submit/migrations/0006_auto_20170216_1911.py
submit/migrations/0007_auto_20170216_1925.py
submit/migrations/0008_auto_20170217_1208.py
submit/migrations/__init__.py
submit/static/submit/google-code-prettify/lang-Splus.js
submit/static/submit/google-code-prettify/lang-aea.js
submit/static/submit/google-code-prettify/lang-agc.js
submit/static/submit/google-code-prettify/lang-apollo.js
submit/static/submit/google-code-prettify/lang-basic.js
submit/static/submit/google-code-prettify/lang-cbm.js
submit/static/submit/google-code-prettify/lang-cl.js
submit/static/submit/google-code-prettify/lang-clj.js
submit/static/submit/google-code-prettify/lang-css.js
submit/static/submit/google-code-prettify/lang-dart.js
submit/static/submit/google-code-prettify/lang-el.js
submit/static/submit/google-code-prettify/lang-erl.js
submit/static/submit/google-code-prettify/lang-erlang.js
submit/static/submit/google-code-prettify/lang-fs.js
submit/static/submit/google-code-prettify/lang-go.js
submit/static/submit/google-code-prettify/lang-hs.js
submit/static/submit/google-code-prettify/lang-lasso.js
submit/static/submit/google-code-prettify/lang-lassoscript.js
submit/static/submit/google-code-prettify/lang-latex.js
submit/static/submit/google-code-prettify/lang-lgt.js
submit/static/submit/google-code-prettify/lang-lisp.js
submit/static/submit/google-code-prettify/lang-ll.js
