Metadata-Version: 1.1
Name: django-trojsten-submit
Version: 0.1.0
Summary: Django app for storing submits and reviews, used in Trojsten seminary web apps
Home-page: https://github.com/trojsten/submit
Author: Mário Lipovský
Author-email: mario.lipovsky@trojsten.sk
License: BSD
Download-URL: https://github.com/trojsten/submit/tarball/0.1
Keywords: submit,review
Platform: UNKNOWN
Classifier: Development Status :: 3 - Alpha
Classifier: Framework :: Django
Classifier: Framework :: Django :: 1.9
Classifier: Intended Audience :: Developers
Classifier: Natural Language :: English
Classifier: Programming Language :: Python :: 2
Classifier: Programming Language :: Python :: 2.7
Classifier: Programming Language :: Python :: 3
Classifier: Programming Language :: Python :: 3.5
